newrelic_extensions/__init__.py
newrelic_extensions/patcher.py
newrelic_extensions/hooks/__init__.py
newrelic_extensions/hooks/base.py
newrelic_extensions/hooks/fabric.py
newrelic_extensions/hooks/kazoo.py
newrelic_extensions/hooks/zag.py
newrelic_extensions-0.1.0.dist-info/METADATA
newrelic_extensions-0.1.0.dist-info/WHEEL
newrelic_extensions-0.1.0.dist-info/entry_points.txt
newrelic_extensions-0.1.0.dist-info/top_level.txt
newrelic_extensions-0.1.0.dist-info/RECORD
